{"imagePath":"hero33_tex.png","width":1024,"SubTexture":[{"width":91,"y":422,"height":167,"name":"51","x":367},{"width":261,"y":0,"height":243,"name":"50","x":710},{"y":631,"frameX":0,"frameY":0,"width":124,"frameWidth":124,"height":171,"name":"49","frameHeight":172,"x":582},{"width":14,"y":66,"height":19,"name":"48","x":1007},{"width":14,"y":43,"height":22,"name":"47","x":1007},{"width":16,"y":0,"height":42,"name":"46","x":1007},{"width":20,"y":288,"height":13,"name":"45","x":980},{"width":24,"y":258,"height":16,"name":"44","x":980},{"width":18,"y":193,"height":38,"name":"43","x":972},{"width":17,"y":258,"height":13,"name":"42","x":1005},{"width":23,"y":275,"height":12,"name":"41","x":980},{"width":18,"y":193,"height":35,"name":"40","x":991},{"width":9,"y":86,"height":13,"name":"39","x":1007},{"width":18,"y":272,"height":12,"name":"38","x":1005},{"width":20,"y":229,"height":28,"name":"37","x":991},{"width":139,"y":244,"height":395,"name":"36","x":710},{"width":96,"y":800,"height":110,"name":"35","x":300},{"width":111,"y":316,"height":314,"name":"34","x":582},{"width":60,"y":775,"height":44,"name":"33","x":955},{"width":62,"y":699,"height":75,"name":"32","x":955},{"width":86,"y":699,"height":159,"name":"31","x":868},{"width":112,"y":316,"height":318,"name":"30","x":469},{"width":210,"y":624,"height":164,"name":"29","x":0},{"width":143,"y":531,"height":167,"name":"28","x":850},{"width":76,"y":635,"height":102,"name":"27","x":503},{"width":110,"y":800,"height":91,"name":"26","x":397},{"width":34,"y":0,"height":163,"name":"25","x":972},{"width":36,"y":164,"height":28,"name":"24","x":972},{"width":88,"y":788,"height":145,"name":"23","x":211},{"width":69,"y":738,"height":48,"name":"20","x":503},{"width":230,"y":0,"height":421,"name":"19","x":238},{"width":129,"y":657,"height":130,"name":"18","x":211},{"width":263,"y":488,"height":135,"name":"17","x":0},{"width":87,"y":640,"height":49,"name":"16","x":707},{"width":89,"y":789,"height":129,"name":"15","x":107},{"width":91,"y":590,"height":38,"name":"14","x":367},{"width":237,"y":0,"height":487,"name":"13","x":0},{"width":56,"y":787,"height":30,"name":"12","x":508},{"width":160,"y":699,"height":120,"name":"11","x":707},{"width":102,"y":422,"height":234,"name":"8","x":264},{"width":129,"y":244,"height":286,"name":"6","x":850},{"width":240,"y":0,"height":315,"name":"5","x":469},{"width":106,"y":789,"height":111,"name":"4","x":0},{"width":135,"y":635,"height":164,"name":"3","x":367},{"width":71,"y":820,"height":19,"name":"1","x":637},{"y":803,"frameX":0,"frameY":-1,"width":71,"frameWidth":71,"height":20,"name":"2","frameHeight":21,"x":565}],"height":934,"name":"hero33"}